diffify_lib/__init__.py
diffify_lib/py.typed
diffify_lib/storage/__init__.py
diffify_lib/storage/s3.py
diffify_lib-0.2.1.dist-info/METADATA
diffify_lib-0.2.1.dist-info/WHEEL
diffify_lib-0.2.1.dist-info/RECORD
