Metadata-Version: 2.3
Name: diffify-lib
Version: 0.2.1
Summary: Code that is used by the backend and Python APIs for diffify.com
Author: Jumping Rivers
Author-email: info@jumpingrivers.com
Requires-Python: >=3.10,<4.0
Classifier: Programming Language :: Python :: 3
Classifier: Programming Language :: Python :: 3.10
Classifier: Programming Language :: Python :: 3.11
Classifier: Programming Language :: Python :: 3.12
Classifier: Programming Language :: Python :: 3.13
Requires-Dist: boto3 (>=1.34.107,<2.0.0)
Requires-Dist: boto3-stubs (>=1.34.108,<2.0.0)
